MANIFEST.in
README.rst
requirements-dev.txt
requirements.txt
setup.py
docs/design_overview.png
docs/ubersmith_api_docs.pdf
tests/system/__init__.py
tests/system/conftest.py
tests/system/test_client.py
tests/system/test_device.py
tests/system/test_general.py
tests/system/test_order.py
tests/system/test_sales.py
tests/system/test_support.py
tests/system/test_uber.py
ubersmith/__init__.py
ubersmith/api.py
ubersmith/clean.py
ubersmith/client.py
ubersmith/compat.py
ubersmith/device.py
ubersmith/exceptions.py
ubersmith/order.py
ubersmith/sales.py
ubersmith/support.py
ubersmith/uber.py
ubersmith/utils.py
ubersmith.egg-info/PKG-INFO
ubersmith.egg-info/SOURCES.txt
ubersmith.egg-info/dependency_links.txt
ubersmith.egg-info/pbr.json
ubersmith.egg-info/requires.txt
ubersmith.egg-info/top_level.txt
ubersmith/calls/__init__.py
ubersmith/calls/client.py
ubersmith/calls/device.py
ubersmith/calls/order.py
ubersmith/calls/sales.py
ubersmith/calls/support.py
ubersmith/calls/uber.py