Metadata-Version: 1.1
Name: ubersmith
Version: 0.3.10
Summary: Client library for the Ubersmith API 2.0
Home-page: https://github.com/jasonkeene/python-ubersmith
Author: Jason Keene
Author-email: jasonkeene@gmail.com
License: MIT License
Keywords: ubersmith
Platform: UNKNOWN
Classifier: Programming Language :: Python
Classifier: Development Status :: 1 - Planning
Classifier: Intended Audience :: Developers
Classifier: License :: OSI Approved :: MIT License
Classifier: Operating System :: OS Independent
